chaosazure/__init__.py
chaosazure/aks/__init__.py
chaosazure/aks/actions.py
chaosazure/aks/constants.py
chaosazure/aks/probes.py
chaosazure/application_gateway/__init__.py
chaosazure/application_gateway/actions.py
chaosazure/application_gateway/constants.py
chaosazure/application_gateway/probes.py
chaosazure/auth/__init__.py
chaosazure/common/__init__.py
chaosazure/common/cleanse.py
chaosazure/common/compute/__init__.py
chaosazure/common/compute/command.py
chaosazure/common/config.py
chaosazure/common/resources/__init__.py
chaosazure/common/resources/graph.py
chaosazure/common/scripts/burn_io.sh
chaosazure/common/scripts/cpu_stress_test.ps1
chaosazure/common/scripts/cpu_stress_test.sh
chaosazure/common/scripts/fill_disk.ps1
chaosazure/common/scripts/fill_disk.sh
chaosazure/common/scripts/network_latency.sh
chaosazure/machine/__init__.py
chaosazure/machine/actions.py
chaosazure/machine/constants.py
chaosazure/machine/probes.py
chaosazure/netapp/__init__.py
chaosazure/netapp/actions.py
chaosazure/netapp/constants.py
chaosazure/netapp/probes.py
chaosazure/postgresql/__init__.py
chaosazure/postgresql/actions.py
chaosazure/postgresql/constants.py
chaosazure/postgresql/probes.py
chaosazure/postgresql_flexible/__init__.py
chaosazure/postgresql_flexible/actions.py
chaosazure/postgresql_flexible/constants.py
chaosazure/postgresql_flexible/probes.py
chaosazure/storage/__init__.py
chaosazure/storage/actions.py
chaosazure/storage/constants.py
chaosazure/storage/probes.py
chaosazure/vmss/__init__.py
chaosazure/vmss/actions.py
chaosazure/vmss/constants.py
chaosazure/vmss/fetcher.py
chaosazure/vmss/probes.py
chaosazure/vmss/records.py
chaosazure/webapp/__init__.py
chaosazure/webapp/actions.py
chaosazure/webapp/constants.py
chaosazure/webapp/probes.py
chaostoolkit_azure-0.17.0.dist-info/METADATA
chaostoolkit_azure-0.17.0.dist-info/WHEEL
chaostoolkit_azure-0.17.0.dist-info/licenses/LICENSE
chaostoolkit_azure-0.17.0.dist-info/RECORD
