Metadata-Version: 2.1
Name: chaostoolkit-azure
Version: 0.17.0
Summary: Chaos Toolkit Extension for Microsoft Azure
Author-Email: Chaos Toolkit <contact@chaostoolkit.org>
License: Apache-2.0
Requires-Python: >=3.8
Requires-Dist: chaostoolkit-lib>=1.42.1
Requires-Dist: azure-mgmt-compute>=30.6.0
Requires-Dist: azure-mgmt-containerservice>=29.1.0
Requires-Dist: azure-mgmt-rdbms>=10.1.0
Requires-Dist: azure-mgmt-network>=25.3.0
Requires-Dist: azure-mgmt-storage>=21.1.0
Requires-Dist: azure-mgmt-resourcegraph>=8.0.0
Requires-Dist: azure-mgmt-web>=7.2.0
Requires-Dist: azure-mgmt-netapp>=12.0.0
Requires-Dist: azure-identity>=1.15.0
Requires-Dist: dateparser>=1.2.0
Requires-Dist: requests>=2.31.0
Requires-Dist: pg8000>=1.30.5
Requires-Dist: azure-keyvault-secrets>=4.8.0
